Metadata-Version: 2.1
Name: simplet5
Version: 0.1.4
Summary: simpleT5 is built on top of PyTorch-lightning ⚡️ and Transformers 🤗 that lets you quickly train your T5 models.
Home-page: https://github.com/Shivanandroy/simpleT5
Author: Shivanand Roy
Author-email: shivanandroy.official@gmail.com
License: apache-2.0
Project-URL: Repo, https://github.com/Shivanandroy/simpleT5
Project-URL: Bug Tracker, https://github.com/Shivanandroy/simpleT5/issues
Keywords: T5,simpleT5,transformers,NLP,finetune,fine-tuning,pytorch,summarization,translation,training,classification,Q&A,inference,fast inference
Platform: UNKNOWN
Classifier: Intended Audience :: Developers
Classifier: Topic :: Scientific/Engineering :: Artificial Intelligence
Classifier: License :: OSI Approved :: Apache Software License
Classifier: Programming Language :: Python :: 3
Classifier: Programming Language :: Python :: 3.5
Classifier: Programming Language :: Python :: 3.6
Classifier: Programming Language :: Python :: 3.7
Classifier: Programming Language :: Python :: 3.8
Requires-Python: >=3.5
